{"type":"FeatureCollection","features":[{"type":"Feature","geometry":{"type":"Point","coordinates":[-118.5276,34.288]},"properties":{"dr_number":"191714562","date_occ":"2019-08-28T00:00:00","time_occ_minutes":720,"hour":12,"year":2019,"month":8,"dow":3,"is_weekend":false,"time_bucket":"MIDDAY","area_id":"17","area_name":"Devonshire","premise_code":"101","premise_desc":"STREET","address":"REXBON                       RD","cross_street":"LONGACRE                     AV","victim_age":"33","victim_sex":"F","mo_codes":"3037 3004 3026 3101 3401 3701 4026","collision_type":"vehicle-bicycle","severity":"minor_injury","has_pedestrian":false,"has_motorcycle":false,"has_bicycle":true,"is_hit_and_run":false,"is_dui":false}},{"type":"Feature","geometry":{"type":"Point","coordinates":[-118.5362,34.2869]},"properties":{"dr_number":"201705370","date_occ":"2020-02-03T00:00:00","time_occ_minutes":700,"hour":11,"year":2020,"month":2,"dow":1,"is_weekend":false,"time_bucket":"MIDDAY","area_id":"17","area_name":"Devonshire","premise_code":"101","premise_desc":"STREET","address":"RESEDA","cross_street":"BEAUFAIT","victim_age":"16","victim_sex":"M","mo_codes":"3011 3037 3025 3101 4026","collision_type":"vehicle-to-vehicle","severity":"minor_injury","has_pedestrian":false,"has_motorcycle":false,"has_bicycle":false,"is_hit_and_run":false,"is_dui":false}},{"type":"Feature","geometry":{"type":"Point","coordinates":[-118.528,34.2983]},"properties":{"dr_number":"191716639","date_occ":"2019-10-13T00:00:00","time_occ_minutes":1240,"hour":20,"year":2019,"month":10,"dow":0,"is_weekend":true,"time_bucket":"EVENING","area_id":"17","area_name":"Devonshire","premise_code":"101","premise_desc":"STREET","address":"ZELZAH","cross_street":"SESNON","victim_age":null,"victim_sex":"M","mo_codes":"4026 3011 3028 3034 3037 3101 3401 3701 3033","collision_type":"vehicle-to-vehicle","severity":"minor_injury","has_pedestrian":false,"has_motorcycle":false,"has_bicycle":false,"is_hit_and_run":true,"is_dui":false}},{"type":"Feature","geometry":{"type":"Point","coordinates":[-118.5227,34.2904]},"properties":{"dr_number":"191717111","date_occ":"2019-10-15T00:00:00","time_occ_minutes":1035,"hour":17,"year":2019,"month":10,"dow":2,"is_weekend":false,"time_bucket":"PM_PEAK","area_id":"17","area_name":"Devonshire","premise_code":"101","premise_desc":"STREET","address":"RINALDI                      ST","cross_street":"CORBIN                       AV","victim_age":"30","victim_sex":"M","mo_codes":"3004 3028 3030 3037 3101 3401 3701 4017","collision_type":"vehicle-bicycle","severity":"minor_injury","has_pedestrian":false,"has_motorcycle":false,"has_bicycle":true,"is_hit_and_run":false,"is_dui":false}},{"type":"Feature","geometry":{"type":"Point","coordinates":[-118.5282,34.2901]},"properties":{"dr_number":"191719422","date_occ":"2019-12-15T00:00:00","time_occ_minutes":180,"hour":3,"year":2019,"month":12,"dow":0,"is_weekend":true,"time_bucket":"EARLY_MORNING","area_id":"17","area_name":"Devonshire","premise_code":"101","premise_desc":"STREET","address":"ZELZAH                       AV","cross_street":"REXBON                       ST","victim_age":null,"victim_sex":"X","mo_codes":"3011 3037 3028 3030 3101 4017","collision_type":"vehicle-to-vehicle","severity":"minor_injury","has_pedestrian":false,"has_motorcycle":false,"has_bicycle":false,"is_hit_and_run":false,"is_dui":false}},{"type":"Feature","geometry":{"type":"Point","coordinates":[-118.5227,34.2904]},"properties":{"dr_number":"191717635","date_occ":"2019-11-01T00:00:00","time_occ_minutes":1035,"hour":17,"year":2019,"month":11,"dow":5,"is_weekend":false,"time_bucket":"PM_PEAK","area_id":"17","area_name":"Devonshire","premise_code":"101","premise_desc":"STREET","address":"TAMPA                        AV","cross_street":"CHASE                        ST","victim_age":"33","victim_sex":"M","mo_codes":"3004 3036 3030 3028 3101 4017","collision_type":"vehicle-bicycle","severity":"minor_injury","has_pedestrian":false,"has_motorcycle":false,"has_bicycle":true,"is_hit_and_run":false,"is_dui":false}},{"type":"Feature","geometry":{"type":"Point","coordinates":[-118.5227,34.2904]},"properties":{"dr_number":"201714574","date_occ":"2020-10-23T00:00:00","time_occ_minutes":990,"hour":16,"year":2020,"month":10,"dow":5,"is_weekend":false,"time_bucket":"PM_PEAK","area_id":"17","area_name":"Devonshire","premise_code":"101","premise_desc":"STREET","address":"WHITE OAK                    AV","cross_street":"RINALDI                      ST","victim_age":"23","victim_sex":"F","mo_codes":"3004 3037 3025 3101 4026","collision_type":"vehicle-bicycle","severity":"minor_injury","has_pedestrian":false,"has_motorcycle":false,"has_bicycle":true,"is_hit_and_run":false,"is_dui":false}},{"type":"Feature","geometry":{"type":"Point","coordinates":[-118.5234,34.2988]},"properties":{"dr_number":"201710392","date_occ":"2020-06-25T00:00:00","time_occ_minutes":1370,"hour":22,"year":2020,"month":6,"dow":4,"is_weekend":false,"time_bucket":"LATE_NIGHT","area_id":"17","area_name":"Devonshire","premise_code":"101","premise_desc":"STREET","address":"CASCADE CANYON               DR","cross_street":"ORNA                         DR","victim_age":"19","victim_sex":"F","mo_codes":"3004 3030 3028 3101 4026 3037","collision_type":"vehicle-bicycle","severity":"minor_injury","has_pedestrian":false,"has_motorcycle":false,"has_bicycle":true,"is_hit_and_run":false,"is_dui":false}},{"type":"Feature","geometry":{"type":"Point","coordinates":[-118.5257,34.2901]},"properties":{"dr_number":"201714111","date_occ":"2020-10-08T00:00:00","time_occ_minutes":1225,"hour":20,"year":2020,"month":10,"dow":4,"is_weekend":false,"time_bucket":"EVENING","area_id":"17","area_name":"Devonshire","premise_code":"101","premise_desc":"STREET","address":"WOOD RANCH                   RD","cross_street":"MAYERLING                    ST","victim_age":null,"victim_sex":"M","mo_codes":"3034 3011 3037 3026 3101 4026","collision_type":"vehicle-to-vehicle","severity":"minor_injury","has_pedestrian":false,"has_motorcycle":false,"has_bicycle":false,"is_hit_and_run":true,"is_dui":false}},{"type":"Feature","geometry":{"type":"Point","coordinates":[-118.5341,34.2852]},"properties":{"dr_number":"201713868","date_occ":"2020-10-02T00:00:00","time_occ_minutes":435,"hour":7,"year":2020,"month":10,"dow":5,"is_weekend":false,"time_bucket":"AM_PEAK","area_id":"17","area_name":"Devonshire","premise_code":"101","premise_desc":"STREET","address":"RESEDA                       BL","cross_street":"CALLE VISTA                  CI","victim_age":"36","victim_sex":"F","mo_codes":"3004 3036 3029 3026 3101 4026","collision_type":"vehicle-bicycle","severity":"minor_injury","has_pedestrian":false,"has_motorcycle":false,"has_bicycle":true,"is_hit_and_run":false,"is_dui":false}},{"type":"Feature","geometry":{"type":"Point","coordinates":[-118.5328,34.2801]},"properties":{"dr_number":"201715830","date_occ":"2020-11-27T00:00:00","time_occ_minutes":705,"hour":11,"year":2020,"month":11,"dow":5,"is_weekend":false,"time_bucket":"MIDDAY","area_id":"17","area_name":"Devonshire","premise_code":"101","premise_desc":"STREET","address":"18400    HASTINGS                     WY","cross_street":null,"victim_age":"67","victim_sex":"M","mo_codes":"","collision_type":null,"severity":"unknown","has_pedestrian":false,"has_motorcycle":false,"has_bicycle":false,"is_hit_and_run":false,"is_dui":false}},{"type":"Feature","geometry":{"type":"Point","coordinates":[-118.5319,34.2825]},"properties":{"dr_number":"211708720","date_occ":"2021-05-24T00:00:00","time_occ_minutes":590,"hour":9,"year":2021,"month":5,"dow":1,"is_weekend":false,"time_bucket":"AM_PEAK","area_id":"17","area_name":"Devonshire","premise_code":"101","premise_desc":"STREET","address":"CHARLTON                     LN","cross_street":"CHIMINEAS                    AV","victim_age":"76","victim_sex":"M","mo_codes":"3037 3101 3004 3028 4026 3034","collision_type":"vehicle-bicycle","severity":"minor_injury","has_pedestrian":false,"has_motorcycle":false,"has_bicycle":true,"is_hit_and_run":true,"is_dui":false}},{"type":"Feature","geometry":{"type":"Point","coordinates":[-118.5255,34.2823]},"properties":{"dr_number":"211709328","date_occ":"2021-06-10T00:00:00","time_occ_minutes":730,"hour":12,"year":2021,"month":6,"dow":4,"is_weekend":false,"time_bucket":"MIDDAY","area_id":"17","area_name":"Devonshire","premise_code":"101","premise_desc":"STREET","address":"11600    ZELZAH                       AV","cross_street":null,"victim_age":"30","victim_sex":"M","mo_codes":"3011 3025 4026 3034","collision_type":"other","severity":"minor_injury","has_pedestrian":false,"has_motorcycle":false,"has_bicycle":false,"is_hit_and_run":true,"is_dui":false}},{"type":"Feature","geometry":{"type":"Point","coordinates":[-118.5227,34.2904]},"properties":{"dr_number":"211716586","date_occ":"2021-12-29T00:00:00","time_occ_minutes":470,"hour":7,"year":2021,"month":12,"dow":3,"is_weekend":false,"time_bucket":"AM_PEAK","area_id":"17","area_name":"Devonshire","premise_code":"101","premise_desc":"STREET","address":"SESNON                       BL","cross_street":"CASCADE CANYON               DR","victim_age":null,"victim_sex":"M","mo_codes":"3034 3037 3101 3028 3011 4026 3039","collision_type":"vehicle-to-vehicle","severity":"minor_injury","has_pedestrian":false,"has_motorcycle":false,"has_bicycle":false,"is_hit_and_run":true,"is_dui":false}},{"type":"Feature","geometry":{"type":"Point","coordinates":[-118.5247,34.2808]},"properties":{"dr_number":"191711843","date_occ":"2019-06-22T00:00:00","time_occ_minutes":840,"hour":14,"year":2019,"month":6,"dow":6,"is_weekend":true,"time_bucket":"MIDDAY","area_id":"17","area_name":"Devonshire","premise_code":"101","premise_desc":"STREET","address":"ZELZAH                       AV","cross_street":"LERDO                        ST","victim_age":"19","victim_sex":"F","mo_codes":"3101 3401 3701 4026 3011 3037 3034 3028","collision_type":"vehicle-to-vehicle","severity":"minor_injury","has_pedestrian":false,"has_motorcycle":false,"has_bicycle":false,"is_hit_and_run":true,"is_dui":false}},{"type":"Feature","geometry":{"type":"Point","coordinates":[-118.5247,34.2808]},"properties":{"dr_number":"191712344","date_occ":"2019-07-04T00:00:00","time_occ_minutes":420,"hour":7,"year":2019,"month":7,"dow":4,"is_weekend":false,"time_bucket":"AM_PEAK","area_id":"17","area_name":"Devonshire","premise_code":"101","premise_desc":"STREET","address":"ZELZAH                       AV","cross_street":"LERDO                        AV","victim_age":"99","victim_sex":"F","mo_codes":"3011 3037 3034 3030 3028 3101 3401 3701 4026","collision_type":"vehicle-to-vehicle","severity":"minor_injury","has_pedestrian":false,"has_motorcycle":false,"has_bicycle":false,"is_hit_and_run":true,"is_dui":false}},{"type":"Feature","geometry":{"type":"Point","coordinates":[-118.5367,34.2878]},"properties":{"dr_number":"191712498","date_occ":"2019-07-08T00:00:00","time_occ_minutes":425,"hour":7,"year":2019,"month":7,"dow":1,"is_weekend":false,"time_bucket":"AM_PEAK","area_id":"17","area_name":"Devonshire","premise_code":"101","premise_desc":"STREET","address":"DUNNICLIFFE","cross_street":"DARBY","victim_age":"40","victim_sex":"M","mo_codes":"3006 3037 3034 3028 3101 3401 3701 4026","collision_type":"vehicle-to-vehicle","severity":"minor_injury","has_pedestrian":false,"has_motorcycle":false,"has_bicycle":false,"is_hit_and_run":true,"is_dui":false}},{"type":"Feature","geometry":{"type":"Point","coordinates":[-118.5341,34.2852]},"properties":{"dr_number":"221704774","date_occ":"2022-01-18T00:00:00","time_occ_minutes":260,"hour":4,"year":2022,"month":1,"dow":2,"is_weekend":false,"time_bucket":"EARLY_MORNING","area_id":"17","area_name":"Devonshire","premise_code":"101","premise_desc":"STREET","address":"RESEDA                       BL","cross_street":"CALLE VISTA                  CI","victim_age":"23","victim_sex":"M","mo_codes":"3011 3025 3034 3037 3101 4017","collision_type":"vehicle-to-vehicle","severity":"property_damage","has_pedestrian":false,"has_motorcycle":false,"has_bicycle":false,"is_hit_and_run":true,"is_dui":false}},{"type":"Feature","geometry":{"type":"Point","coordinates":[-118.5398,34.2864]},"properties":{"dr_number":"221709040","date_occ":"2022-05-13T00:00:00","time_occ_minutes":714,"hour":11,"year":2022,"month":5,"dow":5,"is_weekend":false,"time_bucket":"MIDDAY","area_id":"17","area_name":"Devonshire","premise_code":"101","premise_desc":"STREET","address":"CALLE VISTA                  CR","cross_street":"RESEDA                       BL","victim_age":"67","victim_sex":"F","mo_codes":"3011 3028 4026 3030 3034 3035 3037","collision_type":"other","severity":"minor_injury","has_pedestrian":false,"has_motorcycle":false,"has_bicycle":false,"is_hit_and_run":true,"is_dui":true}},{"type":"Feature","geometry":{"type":"Point","coordinates":[-118.5227,34.2904]},"properties":{"dr_number":"221711918","date_occ":"2022-08-03T00:00:00","time_occ_minutes":890,"hour":14,"year":2022,"month":8,"dow":3,"is_weekend":false,"time_bucket":"MIDDAY","area_id":"17","area_name":"Devonshire","premise_code":"101","premise_desc":"STREET","address":"NORDHOFF                     ST","cross_street":"BALBOA                       BL","victim_age":"57","victim_sex":"F","mo_codes":"3004 3026 4026 3034 3036 3101","collision_type":"vehicle-bicycle","severity":"minor_injury","has_pedestrian":false,"has_motorcycle":false,"has_bicycle":true,"is_hit_and_run":true,"is_dui":false}},{"type":"Feature","geometry":{"type":"Point","coordinates":[-118.5391,34.2936]},"properties":{"dr_number":"221710074","date_occ":"2022-06-16T00:00:00","time_occ_minutes":880,"hour":14,"year":2022,"month":6,"dow":4,"is_weekend":false,"time_bucket":"MIDDAY","area_id":"17","area_name":"Devonshire","premise_code":"101","premise_desc":"STREET","address":"BEAUFAIT                     AV","cross_street":"EDDLESTON                    DR","victim_age":"25","victim_sex":"M","mo_codes":"4017 3104 3004 3026 3029 3037","collision_type":"other","severity":"minor_injury","has_pedestrian":false,"has_motorcycle":false,"has_bicycle":true,"is_hit_and_run":false,"is_dui":false}},{"type":"Feature","geometry":{"type":"Point","coordinates":[-118.5227,34.2904]},"properties":{"dr_number":"221711071","date_occ":"2022-07-09T00:00:00","time_occ_minutes":1085,"hour":18,"year":2022,"month":7,"dow":6,"is_weekend":true,"time_bucket":"PM_PEAK","area_id":"17","area_name":"Devonshire","premise_code":"102","premise_desc":"SIDEWALK","address":"ENCINO                       AV","cross_street":"RINALDI                      ST","victim_age":null,"victim_sex":"X","mo_codes":"3011 3025 4026 3034 3037 3101","collision_type":"vehicle-to-vehicle","severity":"minor_injury","has_pedestrian":false,"has_motorcycle":false,"has_bicycle":false,"is_hit_and_run":true,"is_dui":false}},{"type":"Feature","geometry":{"type":"Point","coordinates":[-118.5247,34.2807]},"properties":{"dr_number":"241706056","date_occ":"2024-02-19T00:00:00","time_occ_minutes":540,"hour":9,"year":2024,"month":2,"dow":1,"is_weekend":false,"time_bucket":"AM_PEAK","area_id":"17","area_name":"Devonshire","premise_code":"101","premise_desc":"STREET","address":"ZELZAH","cross_street":"LERDO","victim_age":"99","victim_sex":"X","mo_codes":"3028 4026 3034 3037 3011 3103","collision_type":"vehicle-pedestrian","severity":"minor_injury","has_pedestrian":true,"has_motorcycle":false,"has_bicycle":false,"is_hit_and_run":true,"is_dui":false}},{"type":"Feature","geometry":{"type":"Point","coordinates":[-118.5378,34.2982]},"properties":{"dr_number":"221709461","date_occ":"2022-05-28T00:00:00","time_occ_minutes":1275,"hour":21,"year":2022,"month":5,"dow":6,"is_weekend":true,"time_bucket":"EVENING","area_id":"17","area_name":"Devonshire","premise_code":"101","premise_desc":"STREET","address":"SESNON                       BL","cross_street":"LONGACRE                     AV","victim_age":null,"victim_sex":"X","mo_codes":"3011 3028 4017 3030 3034 3037 3101","collision_type":"vehicle-to-vehicle","severity":"minor_injury","has_pedestrian":false,"has_motorcycle":false,"has_bicycle":false,"is_hit_and_run":true,"is_dui":false}},{"type":"Feature","geometry":{"type":"Point","coordinates":[-118.5374,34.2975]},"properties":{"dr_number":"231717894","date_occ":"2023-11-20T00:00:00","time_occ_minutes":480,"hour":8,"year":2023,"month":11,"dow":1,"is_weekend":false,"time_bucket":"AM_PEAK","area_id":"17","area_name":"Devonshire","premise_code":"101","premise_desc":"STREET","address":"CASPIAN                      CT","cross_street":"LONGACRE                     AV","victim_age":"21","victim_sex":"M","mo_codes":"3006 3028 4017 3101","collision_type":"vehicle-to-vehicle","severity":"minor_injury","has_pedestrian":false,"has_motorcycle":false,"has_bicycle":false,"is_hit_and_run":false,"is_dui":false}},{"type":"Feature","geometry":{"type":"Point","coordinates":[-118.5227,34.2904]},"properties":{"dr_number":"231704331","date_occ":"2023-01-09T00:00:00","time_occ_minutes":1390,"hour":23,"year":2023,"month":1,"dow":1,"is_weekend":false,"time_bucket":"LATE_NIGHT","area_id":"17","area_name":"Devonshire","premise_code":"101","premise_desc":"STREET","address":"BALBOA                       BL","cross_street":"KNOLLWOOD                    DR","victim_age":"49","victim_sex":"M","mo_codes":"3004 3025 4017 3037 3101","collision_type":"vehicle-bicycle","severity":"property_damage","has_pedestrian":false,"has_motorcycle":false,"has_bicycle":true,"is_hit_and_run":false,"is_dui":false}},{"type":"Feature","geometry":{"type":"Point","coordinates":[-118.5347,34.2819]},"properties":{"dr_number":"231712687","date_occ":"2023-07-12T00:00:00","time_occ_minutes":1220,"hour":20,"year":2023,"month":7,"dow":3,"is_weekend":false,"time_bucket":"EVENING","area_id":"17","area_name":"Devonshire","premise_code":"101","premise_desc":"STREET","address":"RESEDA                       BL","cross_street":"BRASILIA                     DR","victim_age":"22","victim_sex":"M","mo_codes":"3101 3009 3025 4026 3036","collision_type":"vehicle-to-vehicle","severity":"minor_injury","has_pedestrian":false,"has_motorcycle":false,"has_bicycle":false,"is_hit_and_run":false,"is_dui":false}},{"type":"Feature","geometry":{"type":"Point","coordinates":[-118.5272,34.2982]},"properties":{"dr_number":"231714687","date_occ":"2023-09-01T00:00:00","time_occ_minutes":690,"hour":11,"year":2023,"month":9,"dow":5,"is_weekend":false,"time_bucket":"MIDDAY","area_id":"17","area_name":"Devonshire","premise_code":"101","premise_desc":"STREET","address":"DALI                         DR","cross_street":"CLASSICS                     DR","victim_age":"65","victim_sex":"M","mo_codes":"3011 3028 4026 3034 3037 3102","collision_type":"other","severity":"minor_injury","has_pedestrian":false,"has_motorcycle":true,"has_bicycle":false,"is_hit_and_run":true,"is_dui":false}},{"type":"Feature","geometry":{"type":"Point","coordinates":[-118.5267,34.2867]},"properties":{"dr_number":"231716516","date_occ":"2023-10-16T00:00:00","time_occ_minutes":1330,"hour":22,"year":2023,"month":10,"dow":1,"is_weekend":false,"time_bucket":"LATE_NIGHT","area_id":"17","area_name":"Devonshire","premise_code":"101","premise_desc":"STREET","address":"ZELZAH                       AV","cross_street":"RIDGEWAY                     RD","victim_age":"50","victim_sex":"M","mo_codes":"3012 3028 4026 3034 3037 3101","collision_type":"vehicle-to-vehicle","severity":"minor_injury","has_pedestrian":false,"has_motorcycle":false,"has_bicycle":false,"is_hit_and_run":true,"is_dui":false}},{"type":"Feature","geometry":{"type":"Point","coordinates":[-118.5359,34.2954]},"properties":{"dr_number":"241704900","date_occ":"2024-01-23T00:00:00","time_occ_minutes":450,"hour":7,"year":2024,"month":1,"dow":2,"is_weekend":false,"time_bucket":"AM_PEAK","area_id":"17","area_name":"Devonshire","premise_code":"101","premise_desc":"STREET","address":"LONGACRE                     AV","cross_street":"SHETLAND                     PL","victim_age":"30","victim_sex":"M","mo_codes":"3011 3028 4026 3030 3034 3037","collision_type":"other","severity":"minor_injury","has_pedestrian":false,"has_motorcycle":false,"has_bicycle":false,"is_hit_and_run":true,"is_dui":false}},{"type":"Feature","geometry":{"type":"Point","coordinates":[-118.5367,34.2834]},"properties":{"dr_number":"241709619","date_occ":"2024-05-11T00:00:00","time_occ_minutes":245,"hour":4,"year":2024,"month":5,"dow":6,"is_weekend":true,"time_bucket":"EARLY_MORNING","area_id":"17","area_name":"Devonshire","premise_code":"101","premise_desc":"STREET","address":"BRASILIA                     DR","cross_street":"CASTILLO                     LN","victim_age":"50","victim_sex":"M","mo_codes":"3101 3011 3028 4017 3030 3037","collision_type":"vehicle-to-vehicle","severity":"minor_injury","has_pedestrian":false,"has_motorcycle":false,"has_bicycle":false,"is_hit_and_run":false,"is_dui":false}},{"type":"Feature","geometry":{"type":"Point","coordinates":[-118.5362,34.2869]},"properties":{"dr_number":"101708222","date_occ":"2010-03-16T00:00:00","time_occ_minutes":1050,"hour":17,"year":2010,"month":3,"dow":2,"is_weekend":false,"time_bucket":"PM_PEAK","area_id":"17","area_name":"Devonshire","premise_code":"101","premise_desc":"STREET","address":"RESEDA","cross_street":"BEAUFAIT","victim_age":"23","victim_sex":"M","mo_codes":"","collision_type":null,"severity":"unknown","has_pedestrian":false,"has_motorcycle":false,"has_bicycle":false,"is_hit_and_run":false,"is_dui":false}},{"type":"Feature","geometry":{"type":"Point","coordinates":[-118.5296,34.2909]},"properties":{"dr_number":"101704112","date_occ":"2010-01-03T00:00:00","time_occ_minutes":730,"hour":12,"year":2010,"month":1,"dow":0,"is_weekend":true,"time_bucket":"MIDDAY","area_id":"17","area_name":"Devonshire","premise_code":"101","premise_desc":"STREET","address":"STALLION MEADOW","cross_street":"ZELZAH","victim_age":"38","victim_sex":"M","mo_codes":"","collision_type":null,"severity":"unknown","has_pedestrian":false,"has_motorcycle":false,"has_bicycle":false,"is_hit_and_run":false,"is_dui":false}},{"type":"Feature","geometry":{"type":"Point","coordinates":[-118.5347,34.2819]},"properties":{"dr_number":"101714099","date_occ":"2010-07-04T00:00:00","time_occ_minutes":910,"hour":15,"year":2010,"month":7,"dow":0,"is_weekend":true,"time_bucket":"PM_PEAK","area_id":"17","area_name":"Devonshire","premise_code":"101","premise_desc":"STREET","address":"RESEDA                       BL","cross_street":"ASUNCION                     ST","victim_age":null,"victim_sex":"M","mo_codes":"","collision_type":null,"severity":"unknown","has_pedestrian":false,"has_motorcycle":false,"has_bicycle":false,"is_hit_and_run":false,"is_dui":false}},{"type":"Feature","geometry":{"type":"Point","coordinates":[-118.5347,34.2819]},"properties":{"dr_number":"101721545","date_occ":"2010-11-22T00:00:00","time_occ_minutes":1140,"hour":19,"year":2010,"month":11,"dow":1,"is_weekend":false,"time_bucket":"EVENING","area_id":"17","area_name":"Devonshire","premise_code":"101","premise_desc":"STREET","address":"RESEDA                       BL","cross_street":"ASUNCION                     ST","victim_age":null,"victim_sex":"M","mo_codes":"","collision_type":null,"severity":"unknown","has_pedestrian":false,"has_motorcycle":false,"has_bicycle":false,"is_hit_and_run":false,"is_dui":false}},{"type":"Feature","geometry":{"type":"Point","coordinates":[-118.5362,34.2869]},"properties":{"dr_number":"101713854","date_occ":"2010-06-29T00:00:00","time_occ_minutes":1110,"hour":18,"year":2010,"month":6,"dow":2,"is_weekend":false,"time_bucket":"PM_PEAK","area_id":"17","area_name":"Devonshire","premise_code":"101","premise_desc":"STREET","address":"RESEDA                       BL","cross_street":"BEAUFAIT                     AV","victim_age":"58","victim_sex":"M","mo_codes":"","collision_type":null,"severity":"unknown","has_pedestrian":false,"has_motorcycle":false,"has_bicycle":false,"is_hit_and_run":false,"is_dui":false}},{"type":"Feature","geometry":{"type":"Point","coordinates":[-118.5347,34.2819]},"properties":{"dr_number":"101716662","date_occ":"2010-08-22T00:00:00","time_occ_minutes":1410,"hour":23,"year":2010,"month":8,"dow":0,"is_weekend":true,"time_bucket":"LATE_NIGHT","area_id":"17","area_name":"Devonshire","premise_code":"101","premise_desc":"STREET","address":"RESEDA                       BL","cross_street":"BRASILIA                     DR","victim_age":"50","victim_sex":"F","mo_codes":"","collision_type":null,"severity":"unknown","has_pedestrian":false,"has_motorcycle":false,"has_bicycle":false,"is_hit_and_run":false,"is_dui":false}},{"type":"Feature","geometry":{"type":"Point","coordinates":[-118.5378,34.2982]},"properties":{"dr_number":"101719567","date_occ":"2010-10-15T00:00:00","time_occ_minutes":1030,"hour":17,"year":2010,"month":10,"dow":5,"is_weekend":false,"time_bucket":"PM_PEAK","area_id":"17","area_name":"Devonshire","premise_code":"101","premise_desc":"STREET","address":"SESNON                       BL","cross_street":"LONGACRE                     AV","victim_age":null,"victim_sex":"F","mo_codes":"","collision_type":null,"severity":"unknown","has_pedestrian":false,"has_motorcycle":false,"has_bicycle":false,"is_hit_and_run":false,"is_dui":false}},{"type":"Feature","geometry":{"type":"Point","coordinates":[-118.54,34.2895]},"properties":{"dr_number":"101721989","date_occ":"2010-12-02T00:00:00","time_occ_minutes":495,"hour":8,"year":2010,"month":12,"dow":4,"is_weekend":false,"time_bucket":"AM_PEAK","area_id":"17","area_name":"Devonshire","premise_code":"101","premise_desc":"STREET","address":"DARBY                        AV","cross_street":"BRAEMORE","victim_age":"46","victim_sex":"M","mo_codes":"","collision_type":null,"severity":"unknown","has_pedestrian":false,"has_motorcycle":false,"has_bicycle":false,"is_hit_and_run":false,"is_dui":false}},{"type":"Feature","geometry":{"type":"Point","coordinates":[-118.5272,34.2984]},"properties":{"dr_number":"101723323","date_occ":"2010-12-28T00:00:00","time_occ_minutes":675,"hour":11,"year":2010,"month":12,"dow":2,"is_weekend":false,"time_bucket":"MIDDAY","area_id":"17","area_name":"Devonshire","premise_code":"101","premise_desc":"STREET","address":"SESNON                       BL","cross_street":"CLASSICS                     DR","victim_age":"35","victim_sex":"M","mo_codes":"","collision_type":null,"severity":"unknown","has_pedestrian":false,"has_motorcycle":false,"has_bicycle":false,"is_hit_and_run":false,"is_dui":false}},{"type":"Feature","geometry":{"type":"Point","coordinates":[-118.5315,34.2846]},"properties":{"dr_number":"101714517","date_occ":"2010-07-12T00:00:00","time_occ_minutes":1200,"hour":20,"year":2010,"month":7,"dow":1,"is_weekend":false,"time_bucket":"EVENING","area_id":"17","area_name":"Devonshire","premise_code":"101","premise_desc":"STREET","address":"18300    HAMPTON                      CT","cross_street":null,"victim_age":"61","victim_sex":"F","mo_codes":"","collision_type":null,"severity":"unknown","has_pedestrian":false,"has_motorcycle":false,"has_bicycle":false,"is_hit_and_run":false,"is_dui":false}},{"type":"Feature","geometry":{"type":"Point","coordinates":[-118.5362,34.2869]},"properties":{"dr_number":"111704981","date_occ":"2011-01-19T00:00:00","time_occ_minutes":830,"hour":13,"year":2011,"month":1,"dow":3,"is_weekend":false,"time_bucket":"MIDDAY","area_id":"17","area_name":"Devonshire","premise_code":"101","premise_desc":"STREET","address":"RESEDA","cross_street":"BEAUFAIT","victim_age":null,"victim_sex":"M","mo_codes":"1501","collision_type":"other","severity":"unknown","has_pedestrian":false,"has_motorcycle":false,"has_bicycle":false,"is_hit_and_run":false,"is_dui":false}},{"type":"Feature","geometry":{"type":"Point","coordinates":[-118.5378,34.2982]},"properties":{"dr_number":"111711425","date_occ":"2011-05-25T00:00:00","time_occ_minutes":880,"hour":14,"year":2011,"month":5,"dow":3,"is_weekend":false,"time_bucket":"MIDDAY","area_id":"17","area_name":"Devonshire","premise_code":"101","premise_desc":"STREET","address":"LONGACRE                     AV","cross_street":"SESNON                       BL","victim_age":"99","victim_sex":"F","mo_codes":"","collision_type":null,"severity":"unknown","has_pedestrian":false,"has_motorcycle":false,"has_bicycle":false,"is_hit_and_run":false,"is_dui":false}},{"type":"Feature","geometry":{"type":"Point","coordinates":[-118.5227,34.2904]},"properties":{"dr_number":"111712693","date_occ":"2011-06-18T00:00:00","time_occ_minutes":920,"hour":15,"year":2011,"month":6,"dow":6,"is_weekend":true,"time_bucket":"PM_PEAK","area_id":"17","area_name":"Devonshire","premise_code":"102","premise_desc":"SIDEWALK","address":"SESNON","cross_street":"LAWRENCE","victim_age":null,"victim_sex":"M","mo_codes":"1501","collision_type":"other","severity":"unknown","has_pedestrian":false,"has_motorcycle":false,"has_bicycle":false,"is_hit_and_run":false,"is_dui":false}},{"type":"Feature","geometry":{"type":"Point","coordinates":[-118.5276,34.288]},"properties":{"dr_number":"111713463","date_occ":"2011-07-04T00:00:00","time_occ_minutes":580,"hour":9,"year":2011,"month":7,"dow":1,"is_weekend":false,"time_bucket":"AM_PEAK","area_id":"17","area_name":"Devonshire","premise_code":"101","premise_desc":"STREET","address":"ZELZAH                       AV","cross_street":"REXBON                       RD","victim_age":"50","victim_sex":"M","mo_codes":"","collision_type":null,"severity":"unknown","has_pedestrian":false,"has_motorcycle":false,"has_bicycle":false,"is_hit_and_run":false,"is_dui":false}},{"type":"Feature","geometry":{"type":"Point","coordinates":[-118.5392,34.2834]},"properties":{"dr_number":"111720596","date_occ":"2011-11-21T00:00:00","time_occ_minutes":1410,"hour":23,"year":2011,"month":11,"dow":1,"is_weekend":false,"time_bucket":"LATE_NIGHT","area_id":"17","area_name":"Devonshire","premise_code":"101","premise_desc":"STREET","address":"BRASILIA                     DR","cross_street":"SIERRA MORENA                CT","victim_age":"20","victim_sex":"F","mo_codes":"","collision_type":null,"severity":"unknown","has_pedestrian":false,"has_motorcycle":false,"has_bicycle":false,"is_hit_and_run":false,"is_dui":false}},{"type":"Feature","geometry":{"type":"Point","coordinates":[-118.5364,34.2899]},"properties":{"dr_number":"121707314","date_occ":"2012-03-02T00:00:00","time_occ_minutes":1020,"hour":17,"year":2012,"month":3,"dow":5,"is_weekend":false,"time_bucket":"PM_PEAK","area_id":"17","area_name":"Devonshire","premise_code":"101","premise_desc":"STREET","address":"EDDLESTON","cross_street":"BEAUFAIT","victim_age":"47","victim_sex":"M","mo_codes":"3006 3030 3037 3101 3401 3701","collision_type":"vehicle-to-vehicle","severity":"unknown","has_pedestrian":false,"has_motorcycle":false,"has_bicycle":false,"is_hit_and_run":false,"is_dui":false}},{"type":"Feature","geometry":{"type":"Point","coordinates":[-118.5276,34.288]},"properties":{"dr_number":"121716136","date_occ":"2012-08-20T00:00:00","time_occ_minutes":640,"hour":10,"year":2012,"month":8,"dow":1,"is_weekend":false,"time_bucket":"MIDDAY","area_id":"17","area_name":"Devonshire","premise_code":"101","premise_desc":"STREET","address":"LONGACRE","cross_street":"REXBON","victim_age":null,"victim_sex":"X","mo_codes":"3011 3034 3028 3037 3101 3401 3701","collision_type":"vehicle-to-vehicle","severity":"unknown","has_pedestrian":false,"has_motorcycle":false,"has_bicycle":false,"is_hit_and_run":true,"is_dui":false}},{"type":"Feature","geometry":{"type":"Point","coordinates":[-118.5318,34.2809]},"properties":{"dr_number":"121713443","date_occ":"2012-06-27T00:00:00","time_occ_minutes":1040,"hour":17,"year":2012,"month":6,"dow":3,"is_weekend":false,"time_bucket":"PM_PEAK","area_id":"17","area_name":"Devonshire","premise_code":"101","premise_desc":"STREET","address":"SANDRINGHAM                  CT","cross_street":"CHIMINEAS                    AV","victim_age":"43","victim_sex":"M","mo_codes":"","collision_type":null,"severity":"unknown","has_pedestrian":false,"has_motorcycle":false,"has_bicycle":false,"is_hit_and_run":false,"is_dui":false}},{"type":"Feature","geometry":{"type":"Point","coordinates":[-118.5398,34.2864]},"properties":{"dr_number":"121711410","date_occ":"2012-05-19T00:00:00","time_occ_minutes":600,"hour":10,"year":2012,"month":5,"dow":6,"is_weekend":true,"time_bucket":"MIDDAY","area_id":"17","area_name":"Devonshire","premise_code":"101","premise_desc":"STREET","address":"KILLIMORE                    AV","cross_street":"CALLE VISTA                  CR","victim_age":"28","victim_sex":"M","mo_codes":"3006 3037 3401 3701 3026 3101","collision_type":"vehicle-to-vehicle","severity":"unknown","has_pedestrian":false,"has_motorcycle":false,"has_bicycle":false,"is_hit_and_run":false,"is_dui":false}},{"type":"Feature","geometry":{"type":"Point","coordinates":[-118.5227,34.2904]},"properties":{"dr_number":"121713651","date_occ":"2012-07-02T00:00:00","time_occ_minutes":425,"hour":7,"year":2012,"month":7,"dow":1,"is_weekend":false,"time_bucket":"AM_PEAK","area_id":"17","area_name":"Devonshire","premise_code":"101","premise_desc":"STREET","address":"MAYERLING","cross_street":"FANDANGO","victim_age":"36","victim_sex":"F","mo_codes":"3037 3026 3401 3701 3011 1300","collision_type":"vehicle-to-vehicle","severity":"unknown","has_pedestrian":false,"has_motorcycle":false,"has_bicycle":false,"is_hit_and_run":false,"is_dui":false}},{"type":"Feature","geometry":{"type":"Point","coordinates":[-118.5341,34.2852]},"properties":{"dr_number":"121714989","date_occ":"2012-07-28T00:00:00","time_occ_minutes":560,"hour":9,"year":2012,"month":7,"dow":6,"is_weekend":true,"time_bucket":"AM_PEAK","area_id":"17","area_name":"Devonshire","premise_code":"101","premise_desc":"STREET","address":"RESEDA                       BL","cross_street":"CALLE VISTA                  CI","victim_age":"55","victim_sex":"M","mo_codes":"3011 3032 3025 3101 3401 3701 4026","collision_type":"vehicle-to-vehicle","severity":"minor_injury","has_pedestrian":false,"has_motorcycle":false,"has_bicycle":false,"is_hit_and_run":false,"is_dui":false}},{"type":"Feature","geometry":{"type":"Point","coordinates":[-118.522,34.2863]},"properties":{"dr_number":"121716171","date_occ":"2012-08-21T00:00:00","time_occ_minutes":450,"hour":7,"year":2012,"month":8,"dow":2,"is_weekend":false,"time_bucket":"AM_PEAK","area_id":"17","area_name":"Devonshire","premise_code":"101","premise_desc":"STREET","address":"MAYERLING","cross_street":"LERDO","victim_age":"41","victim_sex":"M","mo_codes":"3004 3026 3037 3029 3101 3401 3701","collision_type":"vehicle-bicycle","severity":"unknown","has_pedestrian":false,"has_motorcycle":false,"has_bicycle":true,"is_hit_and_run":false,"is_dui":false}},{"type":"Feature","geometry":{"type":"Point","coordinates":[-118.5362,34.2869]},"properties":{"dr_number":"121713574","date_occ":"2012-06-30T00:00:00","time_occ_minutes":1085,"hour":18,"year":2012,"month":6,"dow":6,"is_weekend":true,"time_bucket":"PM_PEAK","area_id":"17","area_name":"Devonshire","premise_code":"101","premise_desc":"STREET","address":"RESEDA                       BL","cross_street":"CHIMINEAS                    AV","victim_age":null,"victim_sex":"M","mo_codes":"3011 3030 3037 3101 3401 3701","collision_type":"vehicle-to-vehicle","severity":"unknown","has_pedestrian":false,"has_motorcycle":false,"has_bicycle":false,"is_hit_and_run":false,"is_dui":false}},{"type":"Feature","geometry":{"type":"Point","coordinates":[-118.5227,34.2904]},"properties":{"dr_number":"131712923","date_occ":"2013-07-10T00:00:00","time_occ_minutes":1395,"hour":23,"year":2013,"month":7,"dow":3,"is_weekend":false,"time_bucket":"LATE_NIGHT","area_id":"17","area_name":"Devonshire","premise_code":"101","premise_desc":"STREET","address":"WOOD RANCH                   RD","cross_street":"MOUNTAIN RAN                 RD","victim_age":"99","victim_sex":"M","mo_codes":"3011 3030 3037 3034 3101 3401 3701 4026","collision_type":"vehicle-to-vehicle","severity":"minor_injury","has_pedestrian":false,"has_motorcycle":false,"has_bicycle":false,"is_hit_and_run":true,"is_dui":false}},{"type":"Feature","geometry":{"type":"Point","coordinates":[-118.5332,34.2853]},"properties":{"dr_number":"131704876","date_occ":"2013-01-20T00:00:00","time_occ_minutes":970,"hour":16,"year":2013,"month":1,"dow":0,"is_weekend":true,"time_bucket":"PM_PEAK","area_id":"17","area_name":"Devonshire","premise_code":"101","premise_desc":"STREET","address":"EDDLESTON                    DR","cross_street":"CHIMINEAS                    AV","victim_age":null,"victim_sex":"M","mo_codes":"3011 3037 3025 3104 3034 4017 3401 3701","collision_type":"vehicle-bicycle","severity":"property_damage","has_pedestrian":false,"has_motorcycle":false,"has_bicycle":true,"is_hit_and_run":true,"is_dui":false}},{"type":"Feature","geometry":{"type":"Point","coordinates":[-118.5208,34.2871]},"properties":{"dr_number":"131715370","date_occ":"2013-09-03T00:00:00","time_occ_minutes":1170,"hour":19,"year":2013,"month":9,"dow":2,"is_weekend":false,"time_bucket":"EVENING","area_id":"17","area_name":"Devonshire","premise_code":"101","premise_desc":"STREET","address":"WOOD RANCH                   RD","cross_street":"MAYERLING                    ST","victim_age":"32","victim_sex":"X","mo_codes":"3011 3030 3037 3101 3401 3701 4017","collision_type":"vehicle-to-vehicle","severity":"minor_injury","has_pedestrian":false,"has_motorcycle":false,"has_bicycle":false,"is_hit_and_run":false,"is_dui":false}},{"type":"Feature","geometry":{"type":"Point","coordinates":[-118.5362,34.2869]},"properties":{"dr_number":"131712066","date_occ":"2013-06-21T00:00:00","time_occ_minutes":90,"hour":1,"year":2013,"month":6,"dow":5,"is_weekend":false,"time_bucket":"EARLY_MORNING","area_id":"17","area_name":"Devonshire","premise_code":"101","premise_desc":"STREET","address":"RESEDA","cross_street":"BEAUFAIT","victim_age":"99","victim_sex":"M","mo_codes":"3011 3034 4026 3037 3101 3401 3701","collision_type":"vehicle-to-vehicle","severity":"minor_injury","has_pedestrian":false,"has_motorcycle":false,"has_bicycle":false,"is_hit_and_run":true,"is_dui":false}},{"type":"Feature","geometry":{"type":"Point","coordinates":[-118.5398,34.2864]},"properties":{"dr_number":"131716515","date_occ":"2013-09-29T00:00:00","time_occ_minutes":725,"hour":12,"year":2013,"month":9,"dow":0,"is_weekend":true,"time_bucket":"MIDDAY","area_id":"17","area_name":"Devonshire","premise_code":"101","premise_desc":"STREET","address":"RESEDA                       BL","cross_street":"CALLE VISTA                  CR","victim_age":"44","victim_sex":"F","mo_codes":"3008 3034 3025 3037 3103 3401 3701 4026","collision_type":"vehicle-pedestrian","severity":"minor_injury","has_pedestrian":true,"has_motorcycle":false,"has_bicycle":false,"is_hit_and_run":true,"is_dui":false}},{"type":"Feature","geometry":{"type":"Point","coordinates":[-118.5341,34.2852]},"properties":{"dr_number":"131714633","date_occ":"2013-08-20T00:00:00","time_occ_minutes":135,"hour":2,"year":2013,"month":8,"dow":2,"is_weekend":false,"time_bucket":"EARLY_MORNING","area_id":"17","area_name":"Devonshire","premise_code":"101","premise_desc":"STREET","address":"RESEDA                       BL","cross_street":"CALLE VISTA                  CI","victim_age":"32","victim_sex":"M","mo_codes":"3011 3030 3037 3034 3028 3101 3401 3701 4026","collision_type":"vehicle-to-vehicle","severity":"minor_injury","has_pedestrian":false,"has_motorcycle":false,"has_bicycle":false,"is_hit_and_run":true,"is_dui":false}},{"type":"Feature","geometry":{"type":"Point","coordinates":[-118.54,34.2931]},"properties":{"dr_number":"131711332","date_occ":"2013-06-03T00:00:00","time_occ_minutes":1320,"hour":22,"year":2013,"month":6,"dow":1,"is_weekend":false,"time_bucket":"LATE_NIGHT","area_id":"17","area_name":"Devonshire","premise_code":"101","premise_desc":"STREET","address":"KIRKCOLM                     LN","cross_street":"EDDLESTON                    DR","victim_age":null,"victim_sex":"M","mo_codes":"3011 3036 3034 3025 4026 4017 3101 3401 3701","collision_type":"vehicle-to-vehicle","severity":"minor_injury","has_pedestrian":false,"has_motorcycle":false,"has_bicycle":false,"is_hit_and_run":true,"is_dui":false}},{"type":"Feature","geometry":{"type":"Point","coordinates":[-118.5362,34.2869]},"properties":{"dr_number":"131712561","date_occ":"2013-07-04T00:00:00","time_occ_minutes":180,"hour":3,"year":2013,"month":7,"dow":4,"is_weekend":false,"time_bucket":"EARLY_MORNING","area_id":"17","area_name":"Devonshire","premise_code":"101","premise_desc":"STREET","address":"RESEDA                       BL","cross_street":"BEAUFAIT                     AV","victim_age":"48","victim_sex":"M","mo_codes":"3011 3037 3034 3028 4026 3030 3101 3401 3701","collision_type":"vehicle-to-vehicle","severity":"minor_injury","has_pedestrian":false,"has_motorcycle":false,"has_bicycle":false,"is_hit_and_run":true,"is_dui":false}},{"type":"Feature","geometry":{"type":"Point","coordinates":[-118.5227,34.2904]},"properties":{"dr_number":"131720385","date_occ":"2013-12-23T00:00:00","time_occ_minutes":670,"hour":11,"year":2013,"month":12,"dow":1,"is_weekend":false,"time_bucket":"MIDDAY","area_id":"17","area_name":"Devonshire","premise_code":"101","premise_desc":"STREET","address":"BRANFORD                     PL","cross_street":"MARVA                        AV","victim_age":"57","victim_sex":"M","mo_codes":"3004 3037 3101 3401 3701 4026","collision_type":"vehicle-bicycle","severity":"minor_injury","has_pedestrian":false,"has_motorcycle":false,"has_bicycle":true,"is_hit_and_run":false,"is_dui":false}},{"type":"Feature","geometry":{"type":"Point","coordinates":[-118.5227,34.2904]},"properties":{"dr_number":"141711396","date_occ":"2014-06-20T00:00:00","time_occ_minutes":240,"hour":4,"year":2014,"month":6,"dow":5,"is_weekend":false,"time_bucket":"EARLY_MORNING","area_id":"17","area_name":"Devonshire","premise_code":"101","premise_desc":"STREET","address":"ZELZAH                       AV","cross_street":"STALLION","victim_age":null,"victim_sex":"M","mo_codes":"3012 3037 3034 3028 3104 3401 3701 4017","collision_type":"vehicle-bicycle","severity":"minor_injury","has_pedestrian":false,"has_motorcycle":false,"has_bicycle":true,"is_hit_and_run":true,"is_dui":false}},{"type":"Feature","geometry":{"type":"Point","coordinates":[-118.5276,34.288]},"properties":{"dr_number":"141716003","date_occ":"2014-10-05T00:00:00","time_occ_minutes":1360,"hour":22,"year":2014,"month":10,"dow":0,"is_weekend":true,"time_bucket":"LATE_NIGHT","area_id":"17","area_name":"Devonshire","premise_code":"101","premise_desc":"STREET","address":"ZELZAH                       AV","cross_street":"REXBON                       RD","victim_age":null,"victim_sex":null,"mo_codes":"3011 3037 3034 3028 3030 3101 3401 3701 4017","collision_type":"vehicle-to-vehicle","severity":"minor_injury","has_pedestrian":false,"has_motorcycle":false,"has_bicycle":false,"is_hit_and_run":true,"is_dui":false}},{"type":"Feature","geometry":{"type":"Point","coordinates":[-118.5329,34.2843]},"properties":{"dr_number":"141715552","date_occ":"2014-09-25T00:00:00","time_occ_minutes":810,"hour":13,"year":2014,"month":9,"dow":4,"is_weekend":false,"time_bucket":"MIDDAY","area_id":"17","area_name":"Devonshire","premise_code":"101","premise_desc":"STREET","address":"18400    HAMPTON                      CT","cross_street":null,"victim_age":"70","victim_sex":"F","mo_codes":"3011 3037 3025 3101 3401 3701 4026","collision_type":"vehicle-to-vehicle","severity":"minor_injury","has_pedestrian":false,"has_motorcycle":false,"has_bicycle":false,"is_hit_and_run":false,"is_dui":false}},{"type":"Feature","geometry":{"type":"Point","coordinates":[-118.5347,34.2819]},"properties":{"dr_number":"141714742","date_occ":"2014-09-07T00:00:00","time_occ_minutes":585,"hour":9,"year":2014,"month":9,"dow":0,"is_weekend":true,"time_bucket":"AM_PEAK","area_id":"17","area_name":"Devonshire","premise_code":"101","premise_desc":"STREET","address":"RESEDA                       BL","cross_street":"BRASILIA                     DR","victim_age":"62","victim_sex":"M","mo_codes":"3018 3037 3034 3024 3103 3401 3701 4026","collision_type":"vehicle-pedestrian","severity":"minor_injury","has_pedestrian":true,"has_motorcycle":false,"has_bicycle":false,"is_hit_and_run":true,"is_dui":false}},{"type":"Feature","geometry":{"type":"Point","coordinates":[-118.5347,34.2819]},"properties":{"dr_number":"141712721","date_occ":"2014-07-21T00:00:00","time_occ_minutes":995,"hour":16,"year":2014,"month":7,"dow":1,"is_weekend":false,"time_bucket":"PM_PEAK","area_id":"17","area_name":"Devonshire","premise_code":"101","premise_desc":"STREET","address":"RESEDA                       BL","cross_street":"BRASILIA                     DR","victim_age":"99","victim_sex":"M","mo_codes":"3011 3037 3034 3028 3101 3401 3701 4026","collision_type":"vehicle-to-vehicle","severity":"minor_injury","has_pedestrian":false,"has_motorcycle":false,"has_bicycle":false,"is_hit_and_run":true,"is_dui":false}},{"type":"Feature","geometry":{"type":"Point","coordinates":[-118.5362,34.2869]},"properties":{"dr_number":"141714832","date_occ":"2014-09-07T00:00:00","time_occ_minutes":800,"hour":13,"year":2014,"month":9,"dow":0,"is_weekend":true,"time_bucket":"MIDDAY","area_id":"17","area_name":"Devonshire","premise_code":"101","premise_desc":"STREET","address":"RESEDA                       BL","cross_street":"CHIMINEAS                    ST","victim_age":null,"victim_sex":"M","mo_codes":"3004 3036 3025 3101 3401 3701 4017","collision_type":"vehicle-bicycle","severity":"property_damage","has_pedestrian":false,"has_motorcycle":false,"has_bicycle":true,"is_hit_and_run":false,"is_dui":false}},{"type":"Feature","geometry":{"type":"Point","coordinates":[-118.5227,34.2904]},"properties":{"dr_number":"141719674","date_occ":"2014-12-29T00:00:00","time_occ_minutes":1380,"hour":23,"year":2014,"month":12,"dow":1,"is_weekend":false,"time_bucket":"LATE_NIGHT","area_id":"17","area_name":"Devonshire","premise_code":"101","premise_desc":"STREET","address":"RINALDI                      ST","cross_street":"HESPERIA                     AV","victim_age":null,"victim_sex":"M","mo_codes":"3011 3037 3030 3024 3101 3401 3701 4026","collision_type":"vehicle-to-vehicle","severity":"minor_injury","has_pedestrian":false,"has_motorcycle":false,"has_bicycle":false,"is_hit_and_run":false,"is_dui":false}},{"type":"Feature","geometry":{"type":"Point","coordinates":[-118.5227,34.2904]},"properties":{"dr_number":"141716313","date_occ":"2014-10-12T00:00:00","time_occ_minutes":1325,"hour":22,"year":2014,"month":10,"dow":0,"is_weekend":true,"time_bucket":"LATE_NIGHT","area_id":"17","area_name":"Devonshire","premise_code":"101","premise_desc":"STREET","address":"ZELZAH                       AV","cross_street":"STALLION MEA                 LN","victim_age":null,"victim_sex":"M","mo_codes":"3011 3028 3030 3033 3034 3037 3101 3401 3701 4026","collision_type":"vehicle-to-vehicle","severity":"minor_injury","has_pedestrian":false,"has_motorcycle":false,"has_bicycle":false,"is_hit_and_run":true,"is_dui":false}},{"type":"Feature","geometry":{"type":"Point","coordinates":[-118.5229,34.2823]},"properties":{"dr_number":"141713182","date_occ":"2014-07-31T00:00:00","time_occ_minutes":1160,"hour":19,"year":2014,"month":7,"dow":4,"is_weekend":false,"time_bucket":"EVENING","area_id":"17","area_name":"Devonshire","premise_code":"101","premise_desc":"STREET","address":"LERDO                        AV","cross_street":"ZELZAH                       AV","victim_age":"35","victim_sex":"M","mo_codes":"3006 3036 3028 3030 3101 3401 3701 4026","collision_type":"vehicle-to-vehicle","severity":"minor_injury","has_pedestrian":false,"has_motorcycle":false,"has_bicycle":false,"is_hit_and_run":false,"is_dui":false}},{"type":"Feature","geometry":{"type":"Point","coordinates":[-118.5229,34.2823]},"properties":{"dr_number":"141713180","date_occ":"2014-07-31T00:00:00","time_occ_minutes":1160,"hour":19,"year":2014,"month":7,"dow":4,"is_weekend":false,"time_bucket":"EVENING","area_id":"17","area_name":"Devonshire","premise_code":"101","premise_desc":"STREET","address":"LERDO                        AV","cross_street":"ZELZAH                       AV","victim_age":"35","victim_sex":"M","mo_codes":"3006 3036 3028 3030 3101 3401 3701 4026","collision_type":"vehicle-to-vehicle","severity":"minor_injury","has_pedestrian":false,"has_motorcycle":false,"has_bicycle":false,"is_hit_and_run":false,"is_dui":false}},{"type":"Feature","geometry":{"type":"Point","coordinates":[-118.5295,34.2936]},"properties":{"dr_number":"141716604","date_occ":"2014-10-19T00:00:00","time_occ_minutes":710,"hour":11,"year":2014,"month":10,"dow":0,"is_weekend":true,"time_bucket":"MIDDAY","area_id":"17","area_name":"Devonshire","premise_code":"101","premise_desc":"STREET","address":"12300    ZELZAH                       AV","cross_street":null,"victim_age":"40","victim_sex":"M","mo_codes":"3011 3037 3034 3028 3101 3401 3701 4017","collision_type":"vehicle-to-vehicle","severity":"minor_injury","has_pedestrian":false,"has_motorcycle":false,"has_bicycle":false,"is_hit_and_run":true,"is_dui":false}},{"type":"Feature","geometry":{"type":"Point","coordinates":[-118.5227,34.2904]},"properties":{"dr_number":"151704588","date_occ":"2015-01-14T00:00:00","time_occ_minutes":1367,"hour":22,"year":2015,"month":1,"dow":3,"is_weekend":false,"time_bucket":"LATE_NIGHT","area_id":"17","area_name":"Devonshire","premise_code":"101","premise_desc":"STREET","address":"EL ORO                       WY","cross_street":"WESTBURY                     DR","victim_age":"38","victim_sex":"M","mo_codes":"3037 3030 3028 3101 3401 3701 4026 3006","collision_type":"vehicle-to-vehicle","severity":"minor_injury","has_pedestrian":false,"has_motorcycle":false,"has_bicycle":false,"is_hit_and_run":false,"is_dui":false}},{"type":"Feature","geometry":{"type":"Point","coordinates":[-118.5398,34.2864]},"properties":{"dr_number":"151706620","date_occ":"2015-02-25T00:00:00","time_occ_minutes":920,"hour":15,"year":2015,"month":2,"dow":3,"is_weekend":false,"time_bucket":"PM_PEAK","area_id":"17","area_name":"Devonshire","premise_code":"101","premise_desc":"STREET","address":"RINALDI                      ST","cross_street":"AMIGO                        AV","victim_age":"56","victim_sex":"M","mo_codes":"3004 3026 3101 3401 3701 4017 3036","collision_type":"vehicle-bicycle","severity":"minor_injury","has_pedestrian":false,"has_motorcycle":false,"has_bicycle":true,"is_hit_and_run":false,"is_dui":false}},{"type":"Feature","geometry":{"type":"Point","coordinates":[-118.5227,34.2904]},"properties":{"dr_number":"151714548","date_occ":"2015-08-15T00:00:00","time_occ_minutes":640,"hour":10,"year":2015,"month":8,"dow":6,"is_weekend":true,"time_bucket":"MIDDAY","area_id":"17","area_name":"Devonshire","premise_code":"101","premise_desc":"STREET","address":"BALBOA                       BL","cross_street":"MIDWOOD                      DR","victim_age":"24","victim_sex":"F","mo_codes":"3004 3025 3101 3401 3701 4017 3037","collision_type":"vehicle-bicycle","severity":"property_damage","has_pedestrian":false,"has_motorcycle":false,"has_bicycle":true,"is_hit_and_run":false,"is_dui":false}},{"type":"Feature","geometry":{"type":"Point","coordinates":[-118.5398,34.2864]},"properties":{"dr_number":"151709326","date_occ":"2015-04-22T00:00:00","time_occ_minutes":645,"hour":10,"year":2015,"month":4,"dow":3,"is_weekend":false,"time_bucket":"MIDDAY","area_id":"17","area_name":"Devonshire","premise_code":"101","premise_desc":"STREET","address":"SAN FERNANDO MISSION         BL","cross_street":"RESEDA                       BL","victim_age":"72","victim_sex":"F","mo_codes":"3004 3037 3026 3101 3401 3701 4017","collision_type":"vehicle-bicycle","severity":"minor_injury","has_pedestrian":false,"has_motorcycle":false,"has_bicycle":true,"is_hit_and_run":false,"is_dui":false}},{"type":"Feature","geometry":{"type":"Point","coordinates":[-118.5347,34.2819]},"properties":{"dr_number":"151716331","date_occ":"2015-09-21T00:00:00","time_occ_minutes":495,"hour":8,"year":2015,"month":9,"dow":1,"is_weekend":false,"time_bucket":"AM_PEAK","area_id":"17","area_name":"Devonshire","premise_code":"101","premise_desc":"STREET","address":"RESEDA                       BL","cross_street":"ASUNCION                     ST","victim_age":"30","victim_sex":"M","mo_codes":"3004 3036 3026 3101 3401 3701 4017","collision_type":"vehicle-bicycle","severity":"minor_injury","has_pedestrian":false,"has_motorcycle":false,"has_bicycle":true,"is_hit_and_run":false,"is_dui":false}},{"type":"Feature","geometry":{"type":"Point","coordinates":[-118.5367,34.2842]},"properties":{"dr_number":"151709255","date_occ":"2015-04-21T00:00:00","time_occ_minutes":675,"hour":11,"year":2015,"month":4,"dow":2,"is_weekend":false,"time_bucket":"MIDDAY","area_id":"17","area_name":"Devonshire","premise_code":"101","premise_desc":"STREET","address":"CASTILLO                     LN","cross_street":"BRASILIA                     DR","victim_age":"60","victim_sex":"M","mo_codes":"","collision_type":null,"severity":"unknown","has_pedestrian":false,"has_motorcycle":false,"has_bicycle":false,"is_hit_and_run":false,"is_dui":false}},{"type":"Feature","geometry":{"type":"Point","coordinates":[-118.5356,34.2852]},"properties":{"dr_number":"151711643","date_occ":"2015-06-16T00:00:00","time_occ_minutes":25,"hour":0,"year":2015,"month":6,"dow":2,"is_weekend":false,"time_bucket":"EARLY_MORNING","area_id":"17","area_name":"Devonshire","premise_code":"101","premise_desc":"STREET","address":"CALLE VISTA                  CI","cross_street":"ENTRADA                      AV","victim_age":null,"victim_sex":"M","mo_codes":"3006 3037 3025 3101 3401 3701 4026","collision_type":"vehicle-to-vehicle","severity":"minor_injury","has_pedestrian":false,"has_motorcycle":false,"has_bicycle":false,"is_hit_and_run":false,"is_dui":false}},{"type":"Feature","geometry":{"type":"Point","coordinates":[-118.5227,34.2904]},"properties":{"dr_number":"151709373","date_occ":"2015-04-23T00:00:00","time_occ_minutes":1050,"hour":17,"year":2015,"month":4,"dow":4,"is_weekend":false,"time_bucket":"PM_PEAK","area_id":"17","area_name":"Devonshire","premise_code":"101","premise_desc":"STREET","address":"RINALDI                      ST","cross_street":"HESPERIA                     AV","victim_age":"62","victim_sex":"M","mo_codes":"3018 3037 3034 3025 3103 3401 3701 4026","collision_type":"vehicle-pedestrian","severity":"minor_injury","has_pedestrian":true,"has_motorcycle":false,"has_bicycle":false,"is_hit_and_run":true,"is_dui":false}},{"type":"Feature","geometry":{"type":"Point","coordinates":[-118.5227,34.2904]},"properties":{"dr_number":"151713051","date_occ":"2015-07-16T00:00:00","time_occ_minutes":655,"hour":10,"year":2015,"month":7,"dow":4,"is_weekend":false,"time_bucket":"MIDDAY","area_id":"17","area_name":"Devonshire","premise_code":"101","premise_desc":"STREET","address":"HAYVENHURST                  AV","cross_street":"RINALDI                      ST","victim_age":"72","victim_sex":"M","mo_codes":"3004 3037 3026 3101 3401 3701 4026","collision_type":"vehicle-bicycle","severity":"minor_injury","has_pedestrian":false,"has_motorcycle":false,"has_bicycle":true,"is_hit_and_run":false,"is_dui":false}},{"type":"Feature","geometry":{"type":"Point","coordinates":[-118.5227,34.2904]},"properties":{"dr_number":"151707113","date_occ":"2015-03-06T00:00:00","time_occ_minutes":1215,"hour":20,"year":2015,"month":3,"dow":5,"is_weekend":false,"time_bucket":"EVENING","area_id":"17","area_name":"Devonshire","premise_code":"101","premise_desc":"STREET","address":"RINALDI                      ST","cross_street":"BALBOA                       BL","victim_age":"42","victim_sex":"M","mo_codes":"3004 3036 3026 3101 3401 3701 4026","collision_type":"vehicle-bicycle","severity":"minor_injury","has_pedestrian":false,"has_motorcycle":false,"has_bicycle":true,"is_hit_and_run":false,"is_dui":false}},{"type":"Feature","geometry":{"type":"Point","coordinates":[-118.5227,34.2904]},"properties":{"dr_number":"151717211","date_occ":"2015-10-09T00:00:00","time_occ_minutes":420,"hour":7,"year":2015,"month":10,"dow":5,"is_weekend":false,"time_bucket":"AM_PEAK","area_id":"17","area_name":"Devonshire","premise_code":"101","premise_desc":"STREET","address":"RINALDI                      ST","cross_street":"HESPERIA                     AV","victim_age":"99","victim_sex":"M","mo_codes":"3011 3034 3025 3101 3401 3701 4026 3037","collision_type":"vehicle-to-vehicle","severity":"minor_injury","has_pedestrian":false,"has_motorcycle":false,"has_bicycle":false,"is_hit_and_run":true,"is_dui":false}},{"type":"Feature","geometry":{"type":"Point","coordinates":[-118.5362,34.2869]},"properties":{"dr_number":"151709603","date_occ":"2015-04-28T00:00:00","time_occ_minutes":1290,"hour":21,"year":2015,"month":4,"dow":2,"is_weekend":false,"time_bucket":"EVENING","area_id":"17","area_name":"Devonshire","premise_code":"101","premise_desc":"STREET","address":"RESEDA                       BL","cross_street":"BEAUFAIT                     AV","victim_age":"20","victim_sex":"F","mo_codes":"3011 3037 3034 3025 3101 3401 3701 4017","collision_type":"vehicle-to-vehicle","severity":"property_damage","has_pedestrian":false,"has_motorcycle":false,"has_bicycle":false,"is_hit_and_run":true,"is_dui":false}},{"type":"Feature","geometry":{"type":"Point","coordinates":[-118.5398,34.2864]},"properties":{"dr_number":"151718679","date_occ":"2015-11-07T00:00:00","time_occ_minutes":775,"hour":12,"year":2015,"month":11,"dow":6,"is_weekend":true,"time_bucket":"MIDDAY","area_id":"17","area_name":"Devonshire","premise_code":"101","premise_desc":"STREET","address":"LASSEN                       ST","cross_street":"HASKELL                      AV","victim_age":"22","victim_sex":"M","mo_codes":"3004 3036 3025 3602 3101 3401 3701 4026","collision_type":"vehicle-bicycle","severity":"minor_injury","has_pedestrian":false,"has_motorcycle":false,"has_bicycle":true,"is_hit_and_run":false,"is_dui":false}},{"type":"Feature","geometry":{"type":"Point","coordinates":[-118.5267,34.2868]},"properties":{"dr_number":"151718731","date_occ":"2015-11-08T00:00:00","time_occ_minutes":730,"hour":12,"year":2015,"month":11,"dow":0,"is_weekend":true,"time_bucket":"MIDDAY","area_id":"17","area_name":"Devonshire","premise_code":"101","premise_desc":"STREET","address":"ZELZAH                       AV","cross_street":"NEWCASTLE                    AV","victim_age":"23","victim_sex":"M","mo_codes":"3011 3037 3034 3028 3101 3401 3701 4026","collision_type":"vehicle-to-vehicle","severity":"minor_injury","has_pedestrian":false,"has_motorcycle":false,"has_bicycle":false,"is_hit_and_run":true,"is_dui":false}},{"type":"Feature","geometry":{"type":"Point","coordinates":[-118.5227,34.2904]},"properties":{"dr_number":"151720038","date_occ":"2015-12-02T00:00:00","time_occ_minutes":1125,"hour":18,"year":2015,"month":12,"dow":3,"is_weekend":false,"time_bucket":"PM_PEAK","area_id":"17","area_name":"Devonshire","premise_code":"101","premise_desc":"STREET","address":"BALBOA","cross_street":"LORILLARD","victim_age":"68","victim_sex":"F","mo_codes":"3004 3036 3024 3101 3401 3701 4019","collision_type":"vehicle-bicycle","severity":"minor_injury","has_pedestrian":false,"has_motorcycle":false,"has_bicycle":true,"is_hit_and_run":false,"is_dui":false}},{"type":"Feature","geometry":{"type":"Point","coordinates":[-118.5243,34.3]},"properties":{"dr_number":"161700747","date_occ":"2016-06-11T00:00:00","time_occ_minutes":250,"hour":4,"year":2016,"month":6,"dow":6,"is_weekend":true,"time_bucket":"EARLY_MORNING","area_id":"17","area_name":"Devonshire","premise_code":"101","premise_desc":"STREET","address":"LOUISE                       AV","cross_street":"SESNON                       BL","victim_age":null,"victim_sex":"M","mo_codes":"3011 3028 3101 3401 3701 4017 3034 3037","collision_type":"vehicle-to-vehicle","severity":"minor_injury","has_pedestrian":false,"has_motorcycle":false,"has_bicycle":false,"is_hit_and_run":true,"is_dui":false}},{"type":"Feature","geometry":{"type":"Point","coordinates":[-118.5266,34.2921]},"properties":{"dr_number":"161707089","date_occ":"2016-03-07T00:00:00","time_occ_minutes":540,"hour":9,"year":2016,"month":3,"dow":1,"is_weekend":false,"time_bucket":"AM_PEAK","area_id":"17","area_name":"Devonshire","premise_code":"101","premise_desc":"STREET","address":"MAYERLING                    ST","cross_street":"WOOD RANCH                   RD","victim_age":null,"victim_sex":"M","mo_codes":"3004 3036 3034 3028 3101 3401 3701 4026","collision_type":"vehicle-bicycle","severity":"minor_injury","has_pedestrian":false,"has_motorcycle":false,"has_bicycle":true,"is_hit_and_run":true,"is_dui":false}},{"type":"Feature","geometry":{"type":"Point","coordinates":[-118.5227,34.2904]},"properties":{"dr_number":"161708192","date_occ":"2016-03-26T00:00:00","time_occ_minutes":1405,"hour":23,"year":2016,"month":3,"dow":6,"is_weekend":true,"time_bucket":"LATE_NIGHT","area_id":"17","area_name":"Devonshire","premise_code":"101","premise_desc":"STREET","address":"SESNON                       BL","cross_street":"CASCADE                      DR","victim_age":"49","victim_sex":"M","mo_codes":"3004 3036 3026 3101 3401 3701 4017","collision_type":"vehicle-bicycle","severity":"minor_injury","has_pedestrian":false,"has_motorcycle":false,"has_bicycle":true,"is_hit_and_run":false,"is_dui":false}},{"type":"Feature","geometry":{"type":"Point","coordinates":[-118.5227,34.2895]},"properties":{"dr_number":"161708193","date_occ":"2016-03-26T00:00:00","time_occ_minutes":1360,"hour":22,"year":2016,"month":3,"dow":6,"is_weekend":true,"time_bucket":"LATE_NIGHT","area_id":"17","area_name":"Devonshire","premise_code":"101","premise_desc":"STREET","address":"WOOD RANCH                   RD","cross_street":"CANYON COVE                  PL","victim_age":null,"victim_sex":"M","mo_codes":"3011 3034 3028 3101 3401 3701 4017 3037","collision_type":"vehicle-to-vehicle","severity":"minor_injury","has_pedestrian":false,"has_motorcycle":false,"has_bicycle":false,"is_hit_and_run":true,"is_dui":false}},{"type":"Feature","geometry":{"type":"Point","coordinates":[-118.5227,34.2904]},"properties":{"dr_number":"161707832","date_occ":"2016-03-22T00:00:00","time_occ_minutes":1315,"hour":21,"year":2016,"month":3,"dow":2,"is_weekend":false,"time_bucket":"EVENING","area_id":"17","area_name":"Devonshire","premise_code":"101","premise_desc":"STREET","address":"SESNON                       BL","cross_street":"JOLETTE                      AV","victim_age":null,"victim_sex":"X","mo_codes":"1402 3011 3037 3030 3034 3028 3101 3401 3701 4026","collision_type":"vehicle-to-vehicle","severity":"minor_injury","has_pedestrian":false,"has_motorcycle":false,"has_bicycle":false,"is_hit_and_run":true,"is_dui":false}},{"type":"Feature","geometry":{"type":"Point","coordinates":[-118.5209,34.2964]},"properties":{"dr_number":"161718108","date_occ":"2016-10-09T00:00:00","time_occ_minutes":60,"hour":1,"year":2016,"month":10,"dow":0,"is_weekend":true,"time_bucket":"EARLY_MORNING","area_id":"17","area_name":"Devonshire","premise_code":"101","premise_desc":"STREET","address":"BRADFORD                     PL","cross_street":"CASCADE CANYON               DR","victim_age":null,"victim_sex":"M","mo_codes":"3011 3028 3034 3037 3101 3401 3701 4017","collision_type":"vehicle-to-vehicle","severity":"minor_injury","has_pedestrian":false,"has_motorcycle":false,"has_bicycle":false,"is_hit_and_run":true,"is_dui":false}},{"type":"Feature","geometry":{"type":"Point","coordinates":[-118.5353,34.2821]},"properties":{"dr_number":"161718610","date_occ":"2016-10-25T00:00:00","time_occ_minutes":460,"hour":7,"year":2016,"month":10,"dow":2,"is_weekend":false,"time_bucket":"AM_PEAK","area_id":"17","area_name":"Devonshire","premise_code":"101","premise_desc":"STREET","address":"18500    BRYMER                       ST","cross_street":null,"victim_age":"44","victim_sex":"M","mo_codes":"1501 3012 3025 3102 3401 3701 4017","collision_type":"vehicle-motorcycle","severity":"property_damage","has_pedestrian":false,"has_motorcycle":true,"has_bicycle":false,"is_hit_and_run":false,"is_dui":false}},{"type":"Feature","geometry":{"type":"Point","coordinates":[-118.5247,34.2808]},"properties":{"dr_number":"161721334","date_occ":"2016-12-19T00:00:00","time_occ_minutes":430,"hour":7,"year":2016,"month":12,"dow":1,"is_weekend":false,"time_bucket":"AM_PEAK","area_id":"17","area_name":"Devonshire","premise_code":"101","premise_desc":"STREET","address":"ZELZAH                       AV","cross_street":"LERDO                        AV","victim_age":"40","victim_sex":"M","mo_codes":"3011 3037 3030 3034 3028 3101 3401 3701 4026","collision_type":"vehicle-to-vehicle","severity":"minor_injury","has_pedestrian":false,"has_motorcycle":false,"has_bicycle":false,"is_hit_and_run":true,"is_dui":false}},{"type":"Feature","geometry":{"type":"Point","coordinates":[-118.5263,34.2868]},"properties":{"dr_number":"161718302","date_occ":"2016-10-20T00:00:00","time_occ_minutes":780,"hour":13,"year":2016,"month":10,"dow":4,"is_weekend":false,"time_bucket":"MIDDAY","area_id":"17","area_name":"Devonshire","premise_code":"101","premise_desc":"STREET","address":"RIDGEWAY                     RD","cross_street":"LERDO                        AV","victim_age":"40","victim_sex":"M","mo_codes":"3011 3037 3030 3028 3034 3602 3101 3401 3701 4026","collision_type":"vehicle-to-vehicle","severity":"minor_injury","has_pedestrian":false,"has_motorcycle":false,"has_bicycle":false,"is_hit_and_run":true,"is_dui":false}},{"type":"Feature","geometry":{"type":"Point","coordinates":[-118.5281,34.2954]},"properties":{"dr_number":"161719888","date_occ":"2016-11-19T00:00:00","time_occ_minutes":570,"hour":9,"year":2016,"month":11,"dow":6,"is_weekend":true,"time_bucket":"AM_PEAK","area_id":"17","area_name":"Devonshire","premise_code":"101","premise_desc":"STREET","address":"DELANTE                      WY","cross_street":"MAYERLING                    ST","victim_age":"56","victim_sex":"M","mo_codes":"3006 3030 3037 3028 3101 3401 3701 4026","collision_type":"vehicle-to-vehicle","severity":"minor_injury","has_pedestrian":false,"has_motorcycle":false,"has_bicycle":false,"is_hit_and_run":false,"is_dui":false}},{"type":"Feature","geometry":{"type":"Point","coordinates":[-118.5398,34.2864]},"properties":{"dr_number":"171708363","date_occ":"2017-03-22T00:00:00","time_occ_minutes":1350,"hour":22,"year":2017,"month":3,"dow":3,"is_weekend":false,"time_bucket":"LATE_NIGHT","area_id":"17","area_name":"Devonshire","premise_code":"101","premise_desc":"STREET","address":"RESEDA","cross_street":"RONALD REAGA                 FY","victim_age":"31","victim_sex":"M","mo_codes":"3004 3030 3028 3101 3401 3701 4015","collision_type":"vehicle-bicycle","severity":"minor_injury","has_pedestrian":false,"has_motorcycle":false,"has_bicycle":true,"is_hit_and_run":false,"is_dui":false}},{"type":"Feature","geometry":{"type":"Point","coordinates":[-118.5263,34.2868]},"properties":{"dr_number":"171720887","date_occ":"2017-10-26T00:00:00","time_occ_minutes":1,"hour":0,"year":2017,"month":10,"dow":4,"is_weekend":false,"time_bucket":"EARLY_MORNING","area_id":"17","area_name":"Devonshire","premise_code":"101","premise_desc":"STREET","address":"RIDGEWAY                     RD","cross_street":"LERDO                        AV","victim_age":"31","victim_sex":"F","mo_codes":"3006 3030 3028 3037 3101 3401 3701 4009","collision_type":"vehicle-to-vehicle","severity":"minor_injury","has_pedestrian":false,"has_motorcycle":false,"has_bicycle":false,"is_hit_and_run":false,"is_dui":false}},{"type":"Feature","geometry":{"type":"Point","coordinates":[-118.5347,34.2819]},"properties":{"dr_number":"171717086","date_occ":"2017-09-08T00:00:00","time_occ_minutes":105,"hour":1,"year":2017,"month":9,"dow":5,"is_weekend":false,"time_bucket":"EARLY_MORNING","area_id":"17","area_name":"Devonshire","premise_code":"101","premise_desc":"STREET","address":"RESEDA                       BL","cross_street":"BRASILIA                     DR","victim_age":null,"victim_sex":"X","mo_codes":"3012 3036 3034 3030 3028 3101 3401 3701 4017","collision_type":"vehicle-to-vehicle","severity":"minor_injury","has_pedestrian":false,"has_motorcycle":false,"has_bicycle":false,"is_hit_and_run":true,"is_dui":false}},{"type":"Feature","geometry":{"type":"Point","coordinates":[-118.5341,34.2852]},"properties":{"dr_number":"171716577","date_occ":"2017-08-29T00:00:00","time_occ_minutes":1022,"hour":17,"year":2017,"month":8,"dow":2,"is_weekend":false,"time_bucket":"PM_PEAK","area_id":"17","area_name":"Devonshire","premise_code":"101","premise_desc":"STREET","address":"RESEDA                       BL","cross_street":"CALLE VISTA                  CI","victim_age":null,"victim_sex":"X","mo_codes":"3011 3037 3029 3034 3026 3101 3401 3701 4017","collision_type":"vehicle-to-vehicle","severity":"minor_injury","has_pedestrian":false,"has_motorcycle":false,"has_bicycle":false,"is_hit_and_run":true,"is_dui":false}},{"type":"Feature","geometry":{"type":"Point","coordinates":[-118.5346,34.2947]},"properties":{"dr_number":"171719616","date_occ":"2017-10-25T00:00:00","time_occ_minutes":1035,"hour":17,"year":2017,"month":10,"dow":3,"is_weekend":false,"time_bucket":"PM_PEAK","area_id":"17","area_name":"Devonshire","premise_code":"101","premise_desc":"STREET","address":"LONGACRE","cross_street":"OLDENBURG","victim_age":"60","victim_sex":"F","mo_codes":"1501 3011 3037 3034 3026 3101 3701 4021 3401","collision_type":"vehicle-to-vehicle","severity":"minor_injury","has_pedestrian":false,"has_motorcycle":false,"has_bicycle":false,"is_hit_and_run":true,"is_dui":false}},{"type":"Feature","geometry":{"type":"Point","coordinates":[-118.5227,34.2904]},"properties":{"dr_number":"171722867","date_occ":"2017-12-27T00:00:00","time_occ_minutes":1100,"hour":18,"year":2017,"month":12,"dow":3,"is_weekend":false,"time_bucket":"PM_PEAK","area_id":"17","area_name":"Devonshire","premise_code":"101","premise_desc":"STREET","address":"TAMPA                        AV","cross_street":"NASHVILLE                    ST","victim_age":"42","victim_sex":"F","mo_codes":"3037 3004 3025 3101 3401 3701 4017","collision_type":"vehicle-bicycle","severity":"property_damage","has_pedestrian":false,"has_motorcycle":false,"has_bicycle":true,"is_hit_and_run":false,"is_dui":false}},{"type":"Feature","geometry":{"type":"Point","coordinates":[-118.5227,34.2904]},"properties":{"dr_number":"181715235","date_occ":"2018-08-18T00:00:00","time_occ_minutes":540,"hour":9,"year":2018,"month":8,"dow":6,"is_weekend":true,"time_bucket":"AM_PEAK","area_id":"17","area_name":"Devonshire","premise_code":"101","premise_desc":"STREET","address":"BARNESTON                    CT","cross_street":"LOUISE                       AV","victim_age":"41","victim_sex":"F","mo_codes":"3006 3030 3028 3037 3101 3401 3701 4017","collision_type":"vehicle-to-vehicle","severity":"minor_injury","has_pedestrian":false,"has_motorcycle":false,"has_bicycle":false,"is_hit_and_run":false,"is_dui":false}},{"type":"Feature","geometry":{"type":"Point","coordinates":[-118.5227,34.2904]},"properties":{"dr_number":"181717028","date_occ":"2018-10-02T00:00:00","time_occ_minutes":1035,"hour":17,"year":2018,"month":10,"dow":2,"is_weekend":false,"time_bucket":"PM_PEAK","area_id":"17","area_name":"Devonshire","premise_code":"101","premise_desc":"STREET","address":"VERMONT                      AV","cross_street":"EXPOSITION                   BL","victim_age":"33","victim_sex":"M","mo_codes":"3036 3003 3026 3029 3101","collision_type":"vehicle-pedestrian","severity":"unknown","has_pedestrian":true,"has_motorcycle":false,"has_bicycle":false,"is_hit_and_run":false,"is_dui":false}},{"type":"Feature","geometry":{"type":"Point","coordinates":[-118.5227,34.2904]},"properties":{"dr_number":"181717329","date_occ":"2018-10-09T00:00:00","time_occ_minutes":635,"hour":10,"year":2018,"month":10,"dow":2,"is_weekend":false,"time_bucket":"MIDDAY","area_id":"17","area_name":"Devonshire","premise_code":"101","premise_desc":"STREET","address":"LOUISE                       AV","cross_street":"LASSEN                       ST","victim_age":"40","victim_sex":"M","mo_codes":"3004 3036 3602 3025 3101 3401 3701 4017","collision_type":"vehicle-bicycle","severity":"property_damage","has_pedestrian":false,"has_motorcycle":false,"has_bicycle":true,"is_hit_and_run":false,"is_dui":false}},{"type":"Feature","geometry":{"type":"Point","coordinates":[-118.5227,34.2904]},"properties":{"dr_number":"181715768","date_occ":"2018-09-04T00:00:00","time_occ_minutes":1190,"hour":19,"year":2018,"month":9,"dow":2,"is_weekend":false,"time_bucket":"EVENING","area_id":"17","area_name":"Devonshire","premise_code":"101","premise_desc":"STREET","address":"WOOD RANCH                   RD","cross_street":"N  MOUNTAIN RAN                 RD","victim_age":"50","victim_sex":"M","mo_codes":"3006 3026 3037 3101 3401 3701 4026","collision_type":"vehicle-to-vehicle","severity":"minor_injury","has_pedestrian":false,"has_motorcycle":false,"has_bicycle":false,"is_hit_and_run":false,"is_dui":false}},{"type":"Feature","geometry":{"type":"Point","coordinates":[-118.5329,34.2878]},"properties":{"dr_number":"181708031","date_occ":"2018-03-24T00:00:00","time_occ_minutes":30,"hour":0,"year":2018,"month":3,"dow":6,"is_weekend":true,"time_bucket":"EARLY_MORNING","area_id":"17","area_name":"Devonshire","premise_code":"101","premise_desc":"STREET","address":"EDDLESTON                    DR","cross_street":"LAUGHTON                     WY","victim_age":null,"victim_sex":"M","mo_codes":"3037 3039 3006 3028 3101 3401 3701 4017","collision_type":"vehicle-to-vehicle","severity":"minor_injury","has_pedestrian":false,"has_motorcycle":false,"has_bicycle":false,"is_hit_and_run":false,"is_dui":false}},{"type":"Feature","geometry":{"type":"Point","coordinates":[-118.5347,34.2819]},"properties":{"dr_number":"181713138","date_occ":"2018-07-09T00:00:00","time_occ_minutes":1065,"hour":17,"year":2018,"month":7,"dow":1,"is_weekend":false,"time_bucket":"PM_PEAK","area_id":"17","area_name":"Devonshire","premise_code":"101","premise_desc":"STREET","address":"RESEDA                       BL","cross_street":"BRASILIA                     DR","victim_age":null,"victim_sex":"X","mo_codes":"3701 3011 3034 3028 3101 3401 4017 3037","collision_type":"vehicle-to-vehicle","severity":"minor_injury","has_pedestrian":false,"has_motorcycle":false,"has_bicycle":false,"is_hit_and_run":true,"is_dui":false}},{"type":"Feature","geometry":{"type":"Point","coordinates":[-118.5347,34.2819]},"properties":{"dr_number":"181719305","date_occ":"2018-11-22T00:00:00","time_occ_minutes":720,"hour":12,"year":2018,"month":11,"dow":4,"is_weekend":false,"time_bucket":"MIDDAY","area_id":"17","area_name":"Devonshire","premise_code":"101","premise_desc":"STREET","address":"RESEDA                       BL","cross_street":"BRASILIA                     DR","victim_age":null,"victim_sex":"M","mo_codes":"3012 3037 3028 3034 3030 3101 3401 3701 4026","collision_type":"vehicle-to-vehicle","severity":"minor_injury","has_pedestrian":false,"has_motorcycle":false,"has_bicycle":false,"is_hit_and_run":true,"is_dui":false}},{"type":"Feature","geometry":{"type":"Point","coordinates":[-118.536,34.2878]},"properties":{"dr_number":"181719484","date_occ":"2018-11-27T00:00:00","time_occ_minutes":1350,"hour":22,"year":2018,"month":11,"dow":2,"is_weekend":false,"time_bucket":"LATE_NIGHT","area_id":"17","area_name":"Devonshire","premise_code":"101","premise_desc":"STREET","address":"BEAUFAIT                     AV","cross_street":"RESEDA                       BL","victim_age":null,"victim_sex":"M","mo_codes":"3006 3028 3037 3101 3401 3701 4017 1501","collision_type":"vehicle-to-vehicle","severity":"minor_injury","has_pedestrian":false,"has_motorcycle":false,"has_bicycle":false,"is_hit_and_run":false,"is_dui":false}},{"type":"Feature","geometry":{"type":"Point","coordinates":[-118.5347,34.2819]},"properties":{"dr_number":"181719249","date_occ":"2018-11-22T00:00:00","time_occ_minutes":1385,"hour":23,"year":2018,"month":11,"dow":4,"is_weekend":false,"time_bucket":"LATE_NIGHT","area_id":"17","area_name":"Devonshire","premise_code":"101","premise_desc":"STREET","address":"RESEDA                       BL","cross_street":"BRASILIA                     RD","victim_age":"27","victim_sex":"M","mo_codes":"3012 3037 3030 3028 3034 3101 3401 3701 4026","collision_type":"vehicle-to-vehicle","severity":"minor_injury","has_pedestrian":false,"has_motorcycle":false,"has_bicycle":false,"is_hit_and_run":true,"is_dui":false}},{"type":"Feature","geometry":{"type":"Point","coordinates":[-118.525,34.289]},"properties":{"dr_number":"191706561","date_occ":"2019-02-26T00:00:00","time_occ_minutes":1135,"hour":18,"year":2019,"month":2,"dow":2,"is_weekend":false,"time_bucket":"PM_PEAK","area_id":"17","area_name":"Devonshire","premise_code":"101","premise_desc":"STREET","address":"REXBON                       RD","cross_street":"ZELZAH                       AV","victim_age":null,"victim_sex":"M","mo_codes":"3011 3037 3034 3028 3101 3401 3701 4026","collision_type":"vehicle-to-vehicle","severity":"minor_injury","has_pedestrian":false,"has_motorcycle":false,"has_bicycle":false,"is_hit_and_run":true,"is_dui":false}},{"type":"Feature","geometry":{"type":"Point","coordinates":[-118.522,34.2863]},"properties":{"dr_number":"191706059","date_occ":"2019-02-15T00:00:00","time_occ_minutes":590,"hour":9,"year":2019,"month":2,"dow":5,"is_weekend":false,"time_bucket":"AM_PEAK","area_id":"17","area_name":"Devonshire","premise_code":"101","premise_desc":"STREET","address":"LERDO                        AV","cross_street":"S  MAYERLING                    ST","victim_age":"59","victim_sex":"F","mo_codes":"3004 3028 3030 3037 3101 3401 3701 4026","collision_type":"vehicle-bicycle","severity":"minor_injury","has_pedestrian":false,"has_motorcycle":false,"has_bicycle":true,"is_hit_and_run":false,"is_dui":false}},{"type":"Feature","geometry":{"type":"Point","coordinates":[-118.5357,34.2815]},"properties":{"dr_number":"191708746","date_occ":"2019-04-13T00:00:00","time_occ_minutes":480,"hour":8,"year":2019,"month":4,"dow":6,"is_weekend":true,"time_bucket":"AM_PEAK","area_id":"17","area_name":"Devonshire","premise_code":"101","premise_desc":"STREET","address":"BRYMER                       ST","cross_street":"CALLE VISTA                  CI","victim_age":"55","victim_sex":"M","mo_codes":"3006 3030 3028 3037 3101 3401 3701 4017","collision_type":"vehicle-to-vehicle","severity":"minor_injury","has_pedestrian":false,"has_motorcycle":false,"has_bicycle":false,"is_hit_and_run":false,"is_dui":false}},{"type":"Feature","geometry":{"type":"Point","coordinates":[-118.5227,34.2904]},"properties":{"dr_number":"191707381","date_occ":"2019-03-14T00:00:00","time_occ_minutes":930,"hour":15,"year":2019,"month":3,"dow":4,"is_weekend":false,"time_bucket":"PM_PEAK","area_id":"17","area_name":"Devonshire","premise_code":"101","premise_desc":"STREET","address":"BALBOA                       BL","cross_street":"RINALDI                      ST","victim_age":"56","victim_sex":"M","mo_codes":"3004 3030 3028 3037 3101 3401 3701 4026","collision_type":"vehicle-bicycle","severity":"minor_injury","has_pedestrian":false,"has_motorcycle":false,"has_bicycle":true,"is_hit_and_run":false,"is_dui":false}},{"type":"Feature","geometry":{"type":"Point","coordinates":[-118.5329,34.2843]},"properties":{"dr_number":"241711155","date_occ":"2024-07-12T00:00:00","time_occ_minutes":1000,"hour":16,"year":2024,"month":7,"dow":5,"is_weekend":false,"time_bucket":"PM_PEAK","area_id":"17","area_name":"Devonshire","premise_code":"101","premise_desc":"STREET","address":"HAMPTON                      CT","cross_street":"CHIMINEAS                    ST","victim_age":null,"victim_sex":"M","mo_codes":"3101 3011 3028 4017 3030 3034 3037","collision_type":"vehicle-to-vehicle","severity":"minor_injury","has_pedestrian":false,"has_motorcycle":false,"has_bicycle":false,"is_hit_and_run":true,"is_dui":false}},{"type":"Feature","geometry":{"type":"Point","coordinates":[-118.5256,34.2901]},"properties":{"dr_number":"251704129","date_occ":"2025-02-18T00:00:00","time_occ_minutes":770,"hour":12,"year":2025,"month":2,"dow":2,"is_weekend":false,"time_bucket":"MIDDAY","area_id":"17","area_name":"Devonshire","premise_code":"101","premise_desc":"STREET","address":"VARA                         PL","cross_street":"MAYERLING                    ST","victim_age":null,"victim_sex":"M","mo_codes":"3006 3028 4026 3034 3037 3101","collision_type":"vehicle-to-vehicle","severity":"minor_injury","has_pedestrian":false,"has_motorcycle":false,"has_bicycle":false,"is_hit_and_run":true,"is_dui":false}},{"type":"Feature","geometry":{"type":"Point","coordinates":[-118.5318,34.2803]},"properties":{"dr_number":"251704179","date_occ":"2025-03-07T00:00:00","time_occ_minutes":1315,"hour":21,"year":2025,"month":3,"dow":5,"is_weekend":false,"time_bucket":"EVENING","area_id":"17","area_name":"Devonshire","premise_code":"101","premise_desc":"STREET","address":"CHIMINEAS                    AV","cross_street":"HASTINGS                     WY","victim_age":"67","victim_sex":"M","mo_codes":"3004 3028 4017 3030 3033 3035 3036","collision_type":"other","severity":"minor_injury","has_pedestrian":false,"has_motorcycle":false,"has_bicycle":true,"is_hit_and_run":false,"is_dui":true}}]}